{
  "component_name": "MC9S08SC4",
  "manufacturer": "Freescale Semiconductor",
  "component_type": "MCU",
  "package": "16-TSSOP",
  "description": "8-bit HCS08 microcontroller with 4KB Flash, 256B RAM, dual TPM modules for motor control",
  "core": "HCS08",
  "parameters": [
    {
      "id": "cpu_freq_max",
      "name": "Maximum CPU Frequency",
      "symbol": "fCPU",
      "category": "Clock",
      "conditions": [
        {
          "condition_text": "No condition",
          "note": null,
          "min": null,
          "typ": null,
          "max": 40,
          "unit": "MHz",
          "selected": 40,
          "override": null
        }
      ]
    },
    {
      "id": "bus_freq_max",
      "name": "Maximum Bus Frequency",
      "symbol": "fBus",
      "category": "Clock",
      "conditions": [
        {
          "condition_text": "No condition",
          "note": null,
          "min": null,
          "typ": null,
          "max": 20,
          "unit": "MHz",
          "selected": 20,
          "override": null
        }
      ]
    },
    {
      "id": "flash_size",
      "name": "Flash Memory Size",
      "symbol": "FLASH",
      "category": "Memory",
      "conditions": [
        {
          "condition_text": "No condition",
          "note": null,
          "min": null,
          "typ": 4096,
          "max": null,
          "unit": "bytes",
          "selected": 4096,
          "override": null
        }
      ]
    },
    {
      "id": "ram_size",
      "name": "RAM Size",
      "symbol": "RAM",
      "category": "Memory",
      "conditions": [
        {
          "condition_text": "No condition",
          "note": null,
          "min": null,
          "typ": 256,
          "max": null,
          "unit": "bytes",
          "selected": 256,
          "override": null
        }
      ]
    },
    {
      "id": "adc_resolution",
      "name": "ADC Resolution",
      "symbol": "ADC",
      "category": "ADC",
      "conditions": [
        {
          "condition_text": "No condition",
          "note": null,
          "min": null,
          "typ": 10,
          "max": null,
          "unit": "bits",
          "selected": 10,
          "override": null
        }
      ]
    },
    {
      "id": "adc_channels",
      "name": "Number of ADC Channels",
      "symbol": "CH",
      "category": "ADC",
      "conditions": [
        {
          "condition_text": "No condition",
          "note": null,
          "min": null,
          "typ": 8,
          "max": null,
          "unit": "channels",
          "selected": 8,
          "override": null
        }
      ]
    },
    {
      "id": "adc_conversion_time",
      "name": "ADC Conversion Time",
      "symbol": "tADC",
      "category": "ADC",
      "conditions": [
        {
          "condition_text": "Short Sample (ADLSMP=0)",
          "note": null,
          "min": null,
          "typ": 20,
          "max": null,
          "unit": "ADCK cycles",
          "selected": 20,
          "override": null
        }
      ]
    },
    {
      "id": "adc_sample_rate",
      "name": "ADC Sample Rate",
      "symbol": "fADCK",
      "category": "ADC",
      "conditions": [
        {
          "condition_text": "High Speed (ADLPC=0)",
          "note": null,
          "min": 0.4,
          "typ": null,
          "max": 8.0,
          "unit": "MHz",
          "selected": 8.0,
          "override": null
        }
      ]
    },
    {
      "id": "pwm_timers",
      "name": "Number of TPM (PWM) Modules",
      "symbol": "TPM",
      "category": "PWM Timer",
      "conditions": [
        {
          "condition_text": "No condition",
          "note": null,
          "min": null,
          "typ": 2,
          "max": null,
          "unit": "modules",
          "selected": 2,
          "override": null
        }
      ]
    },
    {
      "id": "pwm_channels_per_module",
      "name": "PWM Channels per TPM Module",
      "symbol": "CH",
      "category": "PWM Timer",
      "conditions": [
        {
          "condition_text": "No condition",
          "note": null,
          "min": null,
          "typ": 2,
          "max": null,
          "unit": "channels",
          "selected": 2,
          "override": null
        }
      ]
    },
    {
      "id": "pwm_resolution",
      "name": "PWM Timer Resolution",
      "symbol": "Resolution",
      "category": "PWM Timer",
      "conditions": [
        {
          "condition_text": "No condition",
          "note": null,
          "min": null,
          "typ": 16,
          "max": null,
          "unit": "bits",
          "selected": 16,
          "override": null
        }
      ]
    },
    {
      "id": "uart_count",
      "name": "Number of SCI (UART) Interfaces",
      "symbol": "SCI",
      "category": "Communication",
      "conditions": [
        {
          "condition_text": "No condition",
          "note": null,
          "min": null,
          "typ": 1,
          "max": null,
          "unit": "interfaces",
          "selected": 1,
          "override": null
        }
      ]
    },
    {
      "id": "gpio_count",
      "name": "Total GPIO Pins",
      "symbol": "GPIO",
      "category": "GPIO",
      "conditions": [
        {
          "condition_text": "No condition",
          "note": null,
          "min": null,
          "typ": 12,
          "max": null,
          "unit": "pins",
          "selected": 12,
          "override": null
        }
      ]
    },
    {
      "id": "vdd_range",
      "name": "VDD Operating Voltage Range",
      "symbol": "VDD",
      "category": "Power",
      "conditions": [
        {
          "condition_text": "Operating condition",
          "note": null,
          "min": 4.5,
          "typ": null,
          "max": 5.5,
          "unit": "V",
          "selected": 5.5,
          "override": null
        }
      ]
    },
    {
      "id": "idd_run_typical",
      "name": "Run Mode Current",
      "symbol": "RIDD",
      "category": "Power",
      "conditions": [
        {
          "condition_text": "CPU clock 4 MHz, fBus 2 MHz, ICS configured for FBE",
          "note": "All modules except ADC active, does not include dc loads on port pins",
          "min": null,
          "typ": 1.9,
          "max": 2.4,
          "unit": "mA",
          "selected": 1.9,
          "override": null
        }
      ]
    },
    {
      "id": "idd_stop3",
      "name": "Stop3 Mode Supply Current",
      "symbol": "S3IDD",
      "category": "Power",
      "conditions": [
        {
          "condition_text": "25\u00b0C",
          "note": null,
          "min": null,
          "typ": 0.93,
          "max": null,
          "unit": "\u03bcA",
          "selected": 0.93,
          "override": null
        }
      ]
    },
    {
      "id": "temp_range",
      "name": "Operating Temperature Range",
      "symbol": "TA",
      "category": "Temperature",
      "conditions": [
        {
          "condition_text": "M suffix (maximum range)",
          "note": null,
          "min": -40,
          "typ": null,
          "max": 125,
          "unit": "\u00b0C",
          "selected": 125,
          "override": null
        }
      ]
    }
  ]
}